clearCNV/__init__.py
clearCNV/__main__.py
clearCNV/_version.py
clearCNV/cnv_arithmetics.py
clearCNV/cnv_calling.py
clearCNV/matchscores.py
clearCNV/misc.py
clearCNV/util.py
clearCNV/visualize_scores.py
clearCNV/workflow_cnv_calling.py
clearCNV/workflow_reassignment.py
clearCNV/viz_reassignment/__init__.py
clearCNV/viz_reassignment/app.py
clearCNV/viz_reassignment/cache.py
clearCNV/viz_reassignment/callbacks.py
clearCNV/viz_reassignment/settings.py
clearCNV/viz_reassignment/store.py
clearCNV/viz_reassignment/ui.py
clearCNV/viz_reassignment/ui_plots.py
clearCNV/viz_reassignment/assets/bootstrap.min.css
clearCNV/viz_reassignment/assets/clear-cnv.css
clearCNV/viz_reassignment/assets/fontawesome/css/all.min.css
clearCNV/viz_reassignment/assets/fontawesome/webfonts/fa-brands-400.eot
clearCNV/viz_reassignment/assets/fontawesome/webfonts/fa-brands-400.svg
clearCNV/viz_reassignment/assets/fontawesome/webfonts/fa-brands-400.ttf
clearCNV/viz_reassignment/assets/fontawesome/webfonts/fa-brands-400.woff
clearCNV/viz_reassignment/assets/fontawesome/webfonts/fa-brands-400.woff2
clearCNV/viz_reassignment/assets/fontawesome/webfonts/fa-regular-400.eot
clearCNV/viz_reassignment/assets/fontawesome/webfonts/fa-regular-400.svg
clearCNV/viz_reassignment/assets/fontawesome/webfonts/fa-regular-400.ttf
clearCNV/viz_reassignment/assets/fontawesome/webfonts/fa-regular-400.woff
clearCNV/viz_reassignment/assets/fontawesome/webfonts/fa-regular-400.woff2
clearCNV/viz_reassignment/assets/fontawesome/webfonts/fa-solid-900.eot
clearCNV/viz_reassignment/assets/fontawesome/webfonts/fa-solid-900.svg
clearCNV/viz_reassignment/assets/fontawesome/webfonts/fa-solid-900.ttf
clearCNV/viz_reassignment/assets/fontawesome/webfonts/fa-solid-900.woff
clearCNV/viz_reassignment/assets/fontawesome/webfonts/fa-solid-900.woff2
clearCNV/workflow/Snakefile_cnv_calling
clearCNV/workflow/Snakefile_reassignment
clearCNV/workflow/bih_cluster.json
clearCNV/workflow/config_cnv_calling.yml
clearCNV-0.306.dist-info/LICENSE
clearCNV-0.306.dist-info/METADATA
clearCNV-0.306.dist-info/WHEEL
clearCNV-0.306.dist-info/entry_points.txt
clearCNV-0.306.dist-info/top_level.txt
clearCNV-0.306.dist-info/RECORD
