Metadata-Version: 2.1
Name: clearCNV
Version: 0.306
Summary: Clinical sequencing panel CNV caller and visualizer
Home-page: https://github.com/bihealth/clear-CNV
Author: Vinzenz May
Author-email: Vinzenz.May@mdc-berlin.de
Classifier: Development Status :: 4 - Beta
Classifier: Intended Audience :: Developers
Classifier: License :: OSI Approved :: MIT License
Classifier: Natural Language :: English
Classifier: Topic :: Scientific/Engineering :: Bio-Informatics
Classifier: Programming Language :: Python :: 3
Classifier: Programming Language :: Python :: 3.6
Classifier: Programming Language :: Python :: 3.7
Classifier: Programming Language :: Python :: 3.8
Classifier: Programming Language :: Python :: 3.9
Requires-Python: >=3.7
License-File: LICENSE
Requires-Dist: logzero (==1.5.0)
Requires-Dist: numpy (>=1.18.1)
Requires-Dist: pandas (>=1.0.1)
Requires-Dist: scipy (>=1.4.1)
Requires-Dist: scikit-learn (>=0.22.1)
Requires-Dist: seaborn (>=0.10.0)
Requires-Dist: hmmlearn (>=0.2.3)
Requires-Dist: matplotlib (>=3.1.3)
Requires-Dist: plotly (>=4.5.4)
Requires-Dist: snakemake (>=5.9.1)
Requires-Dist: fastcluster
Requires-Dist: regex
Requires-Dist: attrs
Requires-Dist: cattrs
Requires-Dist: dash (==1.21.0)
Requires-Dist: dash-html-components
Requires-Dist: dash-core-components
Requires-Dist: dash-bootstrap-components
Requires-Dist: flask
Requires-Dist: flask-caching
Requires-Dist: werkzeug (==2.0.0)
